conscript/__init__.py
conscript/main.py
conscript-0.1.9.dist-info/licenses/LICENSE
conscript-0.1.9.dist-info/METADATA
conscript-0.1.9.dist-info/WHEEL
conscript-0.1.9.dist-info/entry_points.txt
conscript-0.1.9.dist-info/top_level.txt
conscript-0.1.9.dist-info/RECORD
