Metadata-Version: 2.4
Name: conscript
Version: 0.1.9
Summary: Conscript console scripts in your own Swiss Army Knife.
Home-page: https://github.com/jsirois/conscript
Author: John Sirois
Author-email: john.sirois@gmail.com
Project-URL: Changelog, https://github.com/jsirois/conscript/blob/main/CHANGES.md
Project-URL: Documentation, https://github.com/jsirois/conscript/blob/main/README.md
Classifier: Development Status :: 4 - Beta
Classifier: Intended Audience :: Developers
Classifier: License :: OSI Approved :: Apache Software License
Classifier: Programming Language :: Python
Classifier: Programming Language :: Python :: 2
Classifier: Programming Language :: Python :: 2.7
Classifier: Programming Language :: Python :: 3
Classifier: Programming Language :: Python :: 3.5
Classifier: Programming Language :: Python :: 3.6
Classifier: Programming Language :: Python :: 3.7
Classifier: Programming Language :: Python :: 3.8
Classifier: Programming Language :: Python :: 3.9
Classifier: Programming Language :: Python :: 3.10
Classifier: Programming Language :: Python :: 3.11
Classifier: Programming Language :: Python :: 3.12
Classifier: Programming Language :: Python :: 3.13
Classifier: Programming Language :: Python :: 3.14
Classifier: Programming Language :: Python :: 3.15
Classifier: Topic :: Utilities
Requires-Python: !=3.0.*,!=3.1.*,!=3.2.*,!=3.3.*,!=3.4.*,<3.16,>=2.7
License-File: LICENSE
Requires-Dist: setuptools; python_version <= "3.5"
Requires-Dist: importlib-metadata; python_version == "3.6" or python_version == "3.7"
Dynamic: license-file
